{
    "Cell": " [CELL:014C049B]", 
    "Record Header": {
        "Signature": "REFR", 
        "Data Size": 50, 
        "Record Flags": {}, 
        "FormID": "01821FD2", 
        "Version Control Info": "00 00 00 00"
    }, 
    "NAME - Base": "0terrainUrockUacU04 [STAT:010C07CF]", 
    "XSCL - Scale": 1.750000000000000, 
    "DATA - Position/Rotation": {
        "Position": {
            "X": 112740.062500000000000, 
            "Y": 95033.242188000000000, 
            "Z": 60.982143000000000
        }, 
        "Rotation": {
            "X": 0.000000000000000, 
            "Y": 0.000000000000000, 
            "Z": 39.143600000000000
        }
    }
}
