{
    "Cell": " [CELL:014C166A]", 
    "Record Header": {
        "Signature": "REFR", 
        "Data Size": 50, 
        "Record Flags": {}, 
        "FormID": "01F02FF9", 
        "Version Control Info": "00 00 00 00"
    }, 
    "NAME - Base": "0FloraUBMUgrassU06 [STAT:010C0C7B]", 
    "XSCL - Scale": 1.520000000000000, 
    "DATA - Position/Rotation": {
        "Position": {
            "X": -153811.046875000000000, 
            "Y": 202180.234375000000000, 
            "Z": 1210.128174000000000
        }, 
        "Rotation": {
            "X": 0.000000000000000, 
            "Y": 0.000000000000000, 
            "Z": 332.315300000000000
        }
    }
}
