{
    "Cell": "AssurdirapalVSInnerSShrine [CELL:01480100]", 
    "Record Header": {
        "Signature": "REFR", 
        "Data Size": 40, 
        "Record Flags": {}, 
        "FormID": "018433B0", 
        "Version Control Info": "00 00 00 00"
    }, 
    "NAME - Base": "0ingredUghoulUheartU01 [INGR:010A001E]", 
    "DATA - Position/Rotation": {
        "Position": {
            "X": 4250.337891000000000, 
            "Y": 4366.785156000000000, 
            "Z": 13698.109375000000000
        }, 
        "Rotation": {
            "X": 0.000000000000000, 
            "Y": 0.000000000000000, 
            "Z": 40.100000000000000
        }
    }
}
