{
    "Cell": "FortSFrostmothVSImperialSCultSShrine [CELL:01480533]", 
    "Record Header": {
        "Signature": "REFR", 
        "Data Size": 40, 
        "Record Flags": {}, 
        "FormID": "01F07667", 
        "Version Control Info": "00 00 00 00"
    }, 
    "NAME - Base": "0pUcureUcommonUs [ALCH:010800E4]", 
    "DATA - Position/Rotation": {
        "Position": {
            "X": 3939.092041000000000, 
            "Y": 3416.784424000000000, 
            "Z": 16453.656250000000000
        }, 
        "Rotation": {
            "X": 0.000000000000000, 
            "Y": 0.000000000000000, 
            "Z": 270.000000000000000
        }
    }
}
