{
    "Cell": "AssemanuVSShrine [CELL:014800FC]", 
    "Record Header": {
        "Signature": "REFR", 
        "Data Size": 40, 
        "Record Flags": {}, 
        "FormID": "01843472", 
        "Version Control Info": "00 00 00 00"
    }, 
    "NAME - Base": "0furnU6thUdagothsymbol [STAT:010C0747]", 
    "DATA - Position/Rotation": {
        "Position": {
            "X": 5007.801758000000000, 
            "Y": 3389.745361000000000, 
            "Z": 11963.139648000000000
        }, 
        "Rotation": {
            "X": 0.000000000000000, 
            "Y": 0.000000000000000, 
            "Z": 51.566200000000000
        }
    }
}
