{
    "Cell": " [CELL:014C083C]", 
    "Record Header": {
        "Signature": "REFR", 
        "Data Size": 50, 
        "Record Flags": {}, 
        "FormID": "018361AA", 
        "Version Control Info": "00 00 00 00"
    }, 
    "NAME - Base": "0floraUashtreeU07 [STAT:010C0854]", 
    "XSCL - Scale": 2.000000000000000, 
    "DATA - Position/Rotation": {
        "Position": {
            "X": 66016.703125000000000, 
            "Y": -47231.277344000000000, 
            "Z": 1465.306152000000000
        }, 
        "Rotation": {
            "X": 0.000000000000000, 
            "Y": 0.000000000000000, 
            "Z": 114.591500000000000
        }
    }
}
