{
    "Record Header": {
        "Signature": "NPC_", 
        "Data Size": 356, 
        "Record Flags": {
            "Compressed ": true
        }, 
        "FormID": "012608FB", 
        "Version Control Info": "00 00 00 00"
    }, 
    "EDID - Editor ID": "0larriusSvarro", 
    "FULL - Name": "Larrius Varro", 
    "Model": {
        "MODL - Model FileName": "Characters\\_Male\\skeleton.nif", 
        "MODB - Bound Radius": 84.617172000000000
    }, 
    "ACBS - Configuration": {
        "Flags": {
            "No Rumors": true
        }, 
        "Base spell points": "00000016", 
        "Fatigue": "0000013F", 
        "Barter gold": "00000000", 
        "Level (offset)": 19, 
        "Calc min": "00000001", 
        "Calc max": "00000000"
    }, 
    "Factions": [
        {
            "Faction": "0122000F", 
            "Rank": "04", 
            "Unused": "4F 44 42"
        }, 
        {
            "Faction": "0122001B", 
            "Rank": "00", 
            "Unused": "4F 44 42"
        }
    ], 
    "RNAM - Race": "Imperial [RACE:00000907]", 
    "Items": [
        {
            "Item": "Book1CheapBriefHistoryoftheEmpirev1 [BOOK:00024554]", 
            "Count": 1
        }, 
        {
            "Item": "Beef [INGR:0003365F]", 
            "Count": -1
        }, 
        {
            "Item": "0pUrestoreUfatigueUs [ALCH:01080021]", 
            "Count": 1
        }, 
        {
            "Item": "0pUrestoreUhealthUq [ALCH:010800DF]", 
            "Count": 1
        }, 
        {
            "Item": "0pUrestoreUhealthUe [ALCH:010800E0]", 
            "Count": 1
        }, 
        {
            "Item": "0weUtemreki [WEAP:011001AF]", 
            "Count": 1
        }, 
        {
            "Item": "0imperialSrightSgauntlet [ARMO:01120014]", 
            "Count": 1
        }, 
        {
            "Item": "0imperialSboots [ARMO:01120015]", 
            "Count": 1
        }, 
        {
            "Item": "0imperialShelmetSarmor [ARMO:01120017]", 
            "Count": 1
        }, 
        {
            "Item": "0imperialUgreaves [ARMO:01120045]", 
            "Count": 1
        }, 
        {
            "Item": "0imperialUchainUgreaves [ARMO:011200A4]", 
            "Count": 1
        }, 
        {
            "Item": "0imperialScuirassUarmor [ARMO:011200A6]", 
            "Count": 1
        }, 
        {
            "Item": "0commonUshoesU04 [CLOT:01140007]", 
            "Count": 1
        }, 
        {
            "Item": "0commonUpantsU02 [CLOT:01140013]", 
            "Count": 1
        }
    ], 
    "SCRI - Script": "R0BILLMTWritVarro [SCPT:01F2A3F4]", 
    "AIDT - AI Data": {
        "Aggression": "05", 
        "Confidence": "32", 
        "Energy Level": "32", 
        "Responsibility": "32", 
        "Buys/Sells and Services": {
            "Training": true
        }, 
        "Teaches": "Blade:2", 
        "Maximum training level": "4A", 
        "Unused": "00 00"
    }, 
    "AI Packages": [
        "PKID - AI Package": "MOEatCurrent6x1 [PACK:0106C39C]", 
        "PKID - AI Package": "MOMageRead1x9x1 [PACK:0106C3A8]", 
        "PKID - AI Package": "MOEatCurrent12x1 [PACK:0106C38F]", 
        "PKID - AI Package": "MOMageRead2131 [PACK:0106C3AC]", 
        "PKID - AI Package": "MOMageRead3171 [PACK:0106C3B0]", 
        "PKID - AI Package": "MOEatCurrent21x1 [PACK:0106C3A3]", 
        "PKID - AI Package": "MOSleepCurrent22x8 [PACK:01F8CB97]", 
        "PKID - AI Package": "MOMerchantPackage200 [PACK:0106C3AB]"
    ], 
    "CNAM - Class": "00023787", 
    "DATA - Stats": {
        "Armorer": "2C", 
        "Athletics": "3A", 
        "Blade": "4A", 
        "Block": "40", 
        "Blunt": "30", 
        "Hand to Hand": "07", 
        "Heavy Armor": "40", 
        "Alchemy": "07", 
        "Alteration": "07", 
        "Conjuration": "07", 
        "Destruction": "07", 
        "Illusion": "07", 
        "Mysticism": "07", 
        "Restoration": "07", 
        "Acrobatics": "07", 
        "Light Armor": "07", 
        "Marksman": "22", 
        "Mercantile": "07", 
        "Security": "07", 
        "Sneak": "07", 
        "Speechcraft": "07", 
        "Health": "0000011D", 
        "Unused": "00 00", 
        "Strength": "64", 
        "Intelligence": "2D", 
        "Willpower": "37", 
        "Agility": "42", 
        "Speed": "3C", 
        "Endurance": "62", 
        "Personality": "3D", 
        "Luck": "28"
    }, 
    "HNAM - Hair": "0018A891", 
    "LNAM - Hair length": 0.000000000000000, 
    "ENAM - Eyes": {
        "Eyes #0": "00027309"
    }, 
    "HCLR - Hair color": {
        "Red": "50", 
        "Green": "40", 
        "Blue": "2E", 
        "Unused": "00"
    }, 
    "FaceGen Data": {
        "FGGS - FaceGen Geometry-Symmetric": "00 00 00 00 00 00 00 00 00 00 00 00 00 00 00 00 00 00 00 00 00 00 00 00 00 00 00 00 00 00 00 00 00 00 00 00 00 00 00 00 00 00 00 00 00 00 00 00 00 00 00 00 00 00 00 00 00 00 00 00 00 00 00 00 00 00 00 00 00 00 00 00 00 00 00 00 00 00 00 00 00 00 00 00 00 00 00 00 00 00 00 00 00 00 00 00 00 00 00 00 00 00 00 00 00 00 00 00 00 00 00 00 00 00 00 00 00 00 00 00 00 00 00 00 00 00 00 00 00 00 00 00 00 00 00 00 00 00 00 00 00 00 00 00 00 00 00 00 00 00 00 00 00 00 00 00 00 00 00 00 00 00 00 00 00 00 00 00 00 00 00 00 00 00 00 00 00 00 00 00 00 00 00 00 00 00 00 00 00 00 00 00 00 00 00 00 00 00 00 00", 
        "FGGA - FaceGen Geometry-Asymmetric": "00 00 00 00 00 00 00 00 00 00 00 00 00 00 00 00 00 00 00 00 00 00 00 00 00 00 00 00 00 00 00 00 00 00 00 00 00 00 00 00 00 00 00 00 00 00 00 00 00 00 00 00 00 00 00 00 00 00 00 00 00 00 00 00 00 00 00 00 00 00 00 00 00 00 00 00 00 00 00 00 00 00 00 00 00 00 00 00 00 00 00 00 00 00 00 00 00 00 00 00 00 00 00 00 00 00 00 00 00 00 00 00 00 00 00 00 00 00 00 00", 
        "FGTS - FaceGen Texture-Symmetric": "00 00 00 00 00 00 00 00 00 00 00 00 00 00 00 00 00 00 00 00 00 00 00 00 00 00 00 00 00 00 00 00 00 00 00 00 00 00 00 00 00 00 00 00 00 00 00 00 00 00 00 00 00 00 00 00 00 00 00 00 00 00 00 00 00 00 00 00 00 00 00 00 00 00 00 00 00 00 00 00 00 00 00 00 00 00 00 00 00 00 00 00 00 00 00 00 00 00 00 00 00 00 00 00 00 00 00 00 00 00 00 00 00 00 00 00 00 00 00 00 00 00 00 00 00 00 00 00 00 00 00 00 00 00 00 00 00 00 00 00 00 00 00 00 00 00 00 00 00 00 00 00 00 00 00 00 00 00 00 00 00 00 00 00 00 00 00 00 00 00 00 00 00 00 00 00 00 00 00 00 00 00 00 00 00 00 00 00 00 00 00 00 00 00 00 00 00 00 00 00"
    }, 
    "FNAM - Unknown": "8E 35"
}
