{
    "Record Header": {
        "Signature": "NPC_", 
        "Data Size": 832, 
        "Record Flags": {
            "Compressed ": true
        }, 
        "FormID": "0126047C", 
        "Version Control Info": "00 00 00 00"
    }, 
    "EDID - Editor ID": "0anora", 
    "FULL - Name": "Anora", 
    "Model": {
        "MODL - Model FileName": "Characters\\_Male\\skeleton.nif", 
        "MODB - Bound Radius": 88.323685000000000
    }, 
    "ACBS - Configuration": {
        "Flags": {
            "Female": true, 
            "Auto-calc stats": true, 
            "No Rumors": true
        }, 
        "Base spell points": "0000005F", 
        "Fatigue": "0000010F", 
        "Barter gold": "00000000", 
        "Level (offset)": 15, 
        "Calc min": "00000001", 
        "Calc max": "00000000"
    }, 
    "Factions": [
        {
            "Faction": "01220006", 
            "Rank": "05", 
            "Unused": "4F 44 42"
        }, 
        {
            "Faction": "0122001B", 
            "Rank": "00", 
            "Unused": "4F 44 42"
        }
    ], 
    "RNAM - Race": "Redguard [RACE:00000D43]", 
    "Items": [
        {
            "Item": "fbmwRedDespairAmulet [CLOT:0102BB0D]", 
            "Count": 1
        }, 
        {
            "Item": "0bonemoldTowerShield [ARMO:0104CBFF]", 
            "Count": 1
        }, 
        {
            "Item": "0demonSkatana [WEAP:011000A2]", 
            "Count": 1
        }, 
        {
            "Item": "0bonemoldUarmunTanUcuirass [ARMO:01120065]", 
            "Count": 1
        }, 
        {
            "Item": "0bonemoldUboots [ARMO:01120069]", 
            "Count": 1
        }, 
        {
            "Item": "0shockguardSrobe [CLOT:0114009A]", 
            "Count": 1
        }, 
        {
            "Item": "0randomSgold [LVLI:011A0020]", 
            "Count": 50
        }
    ], 
    "Spells": [
        "SPLO - Spell": "LL2SpellswordLvl100 [LVSP:00056AAC]"
    ], 
    "AIDT - AI Data": {
        "Aggression": "05", 
        "Confidence": "32", 
        "Energy Level": "32", 
        "Responsibility": "32", 
        "Buys/Sells and Services": "00000000", 
        "Teaches": "Armorer:0", 
        "Maximum training level": "00", 
        "Unused": "00 00"
    }, 
    "AI Packages": [
        "PKID - AI Package": "aaaDefaultStayAtEditorLocation [PACK:0002C81C]"
    ], 
    "CNAM - Class": "00023C07", 
    "DATA - Stats": {
        "Armorer": "06", 
        "Athletics": "10", 
        "Blade": "31", 
        "Block": "27", 
        "Blunt": "10", 
        "Hand to Hand": "06", 
        "Heavy Armor": "2C", 
        "Alchemy": "12", 
        "Alteration": "33", 
        "Conjuration": "12", 
        "Destruction": "33", 
        "Illusion": "33", 
        "Mysticism": "12", 
        "Restoration": "33", 
        "Acrobatics": "06", 
        "Light Armor": "0B", 
        "Marksman": "06", 
        "Mercantile": "0B", 
        "Security": "06", 
        "Sneak": "06", 
        "Speechcraft": "06", 
        "Health": "00000081", 
        "Unused": "00 00", 
        "Strength": "3C", 
        "Intelligence": "26", 
        "Willpower": "4D", 
        "Agility": "30", 
        "Speed": "30", 
        "Endurance": "56", 
        "Personality": "28", 
        "Luck": "32"
    }, 
    "HNAM - Hair": "0002C4D0", 
    "LNAM - Hair length": 0.768700000000000, 
    "ENAM - Eyes": {
        "Eyes #0": "00027309"
    }, 
    "HCLR - Hair color": {
        "Red": "21", 
        "Green": "1F", 
        "Blue": "1F", 
        "Unused": "00"
    }, 
    "FaceGen Data": {
        "FGGS - FaceGen Geometry-Symmetric": "63 5C B0 BF 01 69 9F BF BD 83 0F 3F 11 69 C7 3F 86 1E FE 3F 00 A4 BA 3E 76 63 EF BE A3 45 0C C0 F0 37 53 3F C8 80 D0 3F FC AB E2 BE FB B6 78 3F D4 D9 39 3F 74 B3 6F 40 F9 B1 DF 3F 72 EE 38 BF 1E 3E 86 3E D0 91 CE 3E 36 FC C8 3F 34 B0 C5 BF 16 B8 24 3F F1 60 98 3E 42 55 6D 3F C6 E8 AC 3E 48 52 82 BF BE 55 AF BF 9A F6 FA 3E 47 88 16 BF 58 D7 22 BF D6 2A 8C 3F BE 2E E2 3F 7F E3 01 BF 5B AF B4 3F B9 24 10 BF 7F A6 84 3E B0 5D 24 BF 00 00 E7 BD BA 08 57 BF 32 AA 3D BF 04 63 DA 3E 44 F2 97 BF 20 63 E7 3D 78 CF 36 BE 40 0C 3C 3F 60 CB 3C BD 0D 31 19 BF 94 F1 BE BE D8 F7 91 BE 94 5C E4 3E 5C 63 8D BE", 
        "FGGA - FaceGen Geometry-Asymmetric": "E4 FE 17 C0 40 F5 E0 3D 04 06 2B 3E 48 2A 70 BF 16 41 8A BE 2A BC 2B BF 88 16 D8 3D F8 77 9E 3F 70 EB 99 3F 2A 42 45 BF 9B 81 B9 3F C4 CD 23 BF 92 D4 ED BF 1E A5 2D BF C8 63 44 3F E6 32 C1 3F 74 C7 34 BF 94 25 5F BE 82 1D 05 BE 26 D1 A9 3F 18 14 D4 3E 0F ED 61 3F D0 7F 70 3F 28 AA 0C BD F0 05 8B BE DC CC FB 3E A8 7D 6F 3E C0 4E 78 3F 5C 2C B6 BD 7F 6A 47 3F", 
        "FGTS - FaceGen Texture-Symmetric": "F5 99 09 40 8A 45 3A 3F 78 6A EE BC 70 27 3E C0 A7 B4 B0 BF 84 29 CD 3E C4 2B BA BF 8C 9F 1F BF F4 1D 8B BE D6 61 16 BE 0E 99 AF BF 11 D2 D8 3F 48 7D BE 3F B9 63 42 BF E4 EE 70 BF 4F 0C 05 3F 18 A4 B1 BE B2 CD B0 BF 70 E0 B0 3D 18 22 C5 3E A0 B8 35 BE BC 09 0E 3F DC F8 01 40 04 2A C8 3E C8 88 2E 3F 98 86 A8 BF 3E 6A 4D 3F C8 37 D6 BE D0 F5 E0 BE C2 27 33 3F 78 1F 26 3E 4C C3 A1 3E C5 97 82 3F 04 98 68 BF B6 F9 AC 3F 03 D1 CE BE F1 2A 17 3F 70 CA C3 BD 9C E1 94 BE 78 04 30 BE 8F F6 96 3F 3E E1 EF 3E C0 B8 B6 BE E0 72 9A 3D 40 A8 DE 3D 48 E6 AE 3E 98 B4 66 3F 80 64 D6 BC C2 07 21 3F 38 A4 B6 3E"
    }, 
    "FNAM - Unknown": "A9 61"
}
