{
    "Cell": "Odibaal [CELL:014802C6]", 
    "Record Header": {
        "Signature": "REFR", 
        "Data Size": 40, 
        "Record Flags": {}, 
        "FormID": "01849808", 
        "Version Control Info": "00 00 00 00"
    }, 
    "NAME - Base": "NorthMarker [STAT:00000003]", 
    "DATA - Position/Rotation": {
        "Position": {
            "X": -3878.362305000000000, 
            "Y": 78.189034000000000, 
            "Z": -252.669449000000000
        }, 
        "Rotation": {
            "X": 0.000000000000000, 
            "Y": 0.000000000000000, 
            "Z": 245.408500000000000
        }
    }
}
