{
    "Cell": "OldSMournholdXSBazaarSSewers [CELL:014804FB]", 
    "Record Header": {
        "Signature": "REFR", 
        "Data Size": 50, 
        "Record Flags": {}, 
        "FormID": "01F05BC3", 
        "Version Control Info": "00 00 00 00"
    }, 
    "NAME - Base": "0InUOMUplat512 [STAT:010C0AF3]", 
    "XSCL - Scale": 1.130000000000000, 
    "DATA - Position/Rotation": {
        "Position": {
            "X": 2709.381836000000000, 
            "Y": 4382.165527000000000, 
            "Z": 111.358376000000000
        }, 
        "Rotation": {
            "X": 0.000000000000000, 
            "Y": 0.000000000000000, 
            "Z": 0.000000000000000
        }
    }
}
