{
    "Cell": "SadrithSMoraVSTelvanniSCouncilSHouseVSChambers [CELL:01480320]", 
    "Record Header": {
        "Signature": "REFR", 
        "Data Size": 40, 
        "Record Flags": {}, 
        "FormID": "018756AA", 
        "Version Control Info": "00 00 00 00"
    }, 
    "NAME - Base": "0floraUbcUvineU03 [STAT:010C091B]", 
    "DATA - Position/Rotation": {
        "Position": {
            "X": 3993.808594000000000, 
            "Y": 6044.823730000000000, 
            "Z": -41.754276000000000
        }, 
        "Rotation": {
            "X": 0.000000000000000, 
            "Y": 0.000000000000000, 
            "Z": 45.836600000000000
        }
    }
}
