{
    "Cell": " [CELL:014C0E9A]", 
    "Record Header": {
        "Signature": "REFR", 
        "Data Size": 68, 
        "Record Flags": {
            "Visible when distant": true
        }, 
        "FormID": "0183D6A6", 
        "Version Control Info": "00 00 00 00"
    }, 
    "NAME - Base": "0terrainUrockUbcU18 [STAT:010C08FA]", 
    "XLOD - Distant LOD Data": {
        "Unknown #0": 0.000000000000000, 
        "Unknown #1": 0.000000000000000, 
        "Unknown #2": 1.000000000000000
    }, 
    "XSCL - Scale": 1.590000000000000, 
    "DATA - Position/Rotation": {
        "Position": {
            "X": -6077.012695000000000, 
            "Y": -66895.859375000000000, 
            "Z": 400.485504000000000
        }, 
        "Rotation": {
            "X": 345.194400000000000, 
            "Y": 14.805600000000000, 
            "Z": 347.121100000000000
        }
    }
}
