{
    "Topic": "moXdiagXDagothTaunts [DIAL:01F8B563]", 
    "Record Header": {
        "Signature": "INFO", 
        "Data Size": 240, 
        "Record Flags": {}, 
        "FormID": "01F8B568", 
        "Version Control Info": "00 00 00 00"
    }, 
    "DATA - DATA": {
        "Type": "00", 
        "Next Speaker": "00", 
        "Flags": {}
    }, 
    "QSTI - Quest": "moXqueXdagothtalkengine [QUST:01F8B572]", 
    "PNAM - Previous INFO": "01F8B567", 
    "Responses": [
        {
            "TRDT - Response Data": {
                "Emotion Type": "00000000", 
                "Emotion Value": 50, 
                "Unused": "00 00 00 00", 
                "Response number": "01", 
                "Unused": "00 00 00"
            }, 
            "NAM1 - Response Text": "Come. Bring Wraithguard to the Heart Chamber. Together let us free the cursed false gods.", 
            "NAM2 - Actor notes": ""
        }
    ], 
    "Conditions": [
        {
            "Type": "00", 
            "Unused": "00 00 00", 
            "Comparison Value": 1.000000000000000, 
            "Function": "GetIsID:72", 
            "Unused": "00 00", 
            "Parameter #1": "moXDagothTalker "Dagoth Ur" [NPC_:01F8B55B]", 
            "Parameter #2": "00 00 00 00", 
            "Unused": "00000000"
        }, 
        {
            "Type": "00", 
            "Unused": "00 00 00", 
            "Comparison Value": 5.000000000000000, 
            "Function": "GetQuestVariable:79", 
            "Unused": "00 00", 
            "Parameter #1": "moXqueXdagothtalkengine "moXqueXdagothtalkengine" [QUST:01F8B572]", 
            "Parameter #2": "SpeechIndex", 
            "Unused": "00000000"
        }
    ], 
    "Result Script": {
        "SCHR - Basic Script Data": {
            "Unused": "00 00 00 00", 
            "RefCount": 0, 
            "CompiledSize": 0, 
            "VariableCount": 0, 
            "Type": "Object:0"
        }
    }
}
