{
    "Cell": "SeydaSNeenVSForynSGilnithAsSShack [CELL:01480353]", 
    "Record Header": {
        "Signature": "REFR", 
        "Data Size": 50, 
        "Record Flags": {}, 
        "FormID": "0183FE55", 
        "Version Control Info": "00 00 00 00"
    }, 
    "NAME - Base": "0ComUBasketU01UPOS [CONT:011C007B]", 
    "XSCL - Scale": 1.240000000000000, 
    "DATA - Position/Rotation": {
        "Position": {
            "X": 121.479996000000000, 
            "Y": -233.876801000000000, 
            "Z": 56.219891000000000
        }, 
        "Rotation": {
            "X": 0.000000000000000, 
            "Y": 0.000000000000000, 
            "Z": 45.000000000000000
        }
    }
}
