{
    "Cell": " [CELL:014C1071]", 
    "Record Header": {
        "Signature": "REFR", 
        "Data Size": 40, 
        "Record Flags": {}, 
        "FormID": "0180AA04", 
        "Version Control Info": "00 00 00 00"
    }, 
    "NAME - Base": "0floraUrootUwgU01 [STAT:010C0425]", 
    "DATA - Position/Rotation": {
        "Position": {
            "X": -25869.189453000000000, 
            "Y": 26225.710937000000000, 
            "Z": 1336.405518000000000
        }, 
        "Rotation": {
            "X": 342.811300000000000, 
            "Y": 348.540800000000000, 
            "Z": 130.817000000000000
        }
    }
}
