{
    "Cell": " [CELL:014C0173]", 
    "Record Header": {
        "Signature": "ACRE", 
        "Data Size": 40, 
        "Record Flags": {}, 
        "FormID": "01854C1C", 
        "Version Control Info": "00 00 00 00"
    }, 
    "NAME - Base": "0Slaughterfish [CREA:01F0A2A7]", 
    "DATA - Position/Rotation": {
        "Position": {
            "X": 160546.250000000000000, 
            "Y": 55107.039062000000000, 
            "Z": -330.410950000000000
        }, 
        "Rotation": {
            "X": 0.000000000000000, 
            "Y": 0.000000000000000, 
            "Z": 0.000000000000000
        }
    }
}
