{
    "Cell": " [CELL:014C1267]", 
    "Record Header": {
        "Signature": "REFR", 
        "Data Size": 40, 
        "Record Flags": {}, 
        "FormID": "01839D4F", 
        "Version Control Info": "00 00 00 00"
    }, 
    "NAME - Base": "0terrainUrockUbcU15 [STAT:010C08F7]", 
    "DATA - Position/Rotation": {
        "Position": {
            "X": -52753.429687000000000, 
            "Y": -2213.098145000000000, 
            "Z": -29.714859000000000
        }, 
        "Rotation": {
            "X": 0.000000000000000, 
            "Y": 0.000000000000000, 
            "Z": 18.152000000000000
        }
    }
}
