{
    "Cell": "RethanSManor [CELL:014802FE]", 
    "Record Header": {
        "Signature": "REFR", 
        "Data Size": 87, 
        "Record Flags": {
            "Quest item / Persistent reference / Show in Menu": true
        }, 
        "FormID": "01F8B195", 
        "Version Control Info": "00 00 00 00"
    }, 
    "EDID - Editor ID": "fbmwLlirynFendynVendorChestREF", 
    "NAME - Base": "fbmwLlirynFendynVendorChest [CONT:01F8B0B0]", 
    "Ownership": {
        "XOWN - Owner": "0126081C"
    }, 
    "DATA - Position/Rotation": {
        "Position": {
            "X": -614.802734000000000, 
            "Y": 373.455750000000000, 
            "Z": 865.362305000000000
        }, 
        "Rotation": {
            "X": 0.000000000000000, 
            "Y": 0.000000000000000, 
            "Z": 0.000000000000000
        }
    }
}
