{
    "Cell": " [CELL:014C0129]", 
    "Record Header": {
        "Signature": "REFR", 
        "Data Size": 50, 
        "Record Flags": {}, 
        "FormID": "0186D5C2", 
        "Version Control Info": "00 00 00 00"
    }, 
    "NAME - Base": "0ExUbarnaclesU03 [STAT:010C0A71]", 
    "XSCL - Scale": 2.000000000000000, 
    "DATA - Position/Rotation": {
        "Position": {
            "X": 168365.875000000000000, 
            "Y": 2640.811523000000000, 
            "Z": -948.000977000000000
        }, 
        "Rotation": {
            "X": 14.784500000000000, 
            "Y": 8.081600000000000, 
            "Z": 38.711200000000000
        }
    }
}
