{
    "Record Header": {
        "Signature": "LVLI", 
        "Data Size": 142, 
        "Record Flags": {}, 
        "FormID": "011A0051", 
        "Version Control Info": "00 00 00 00"
    }, 
    "EDID - Editor ID": "0lUmUenchantitemUtempleUrank0U1", 
    "LVLD - Chance none": "00", 
    "LVLF - Flags": {
        "Calculate from all levels <= player's level": true, 
        "Calculate for each item in count": true
    }, 
    "Leveled List Entries": [
        {
            "Level": 1, 
            "Unused": "8F 1E", 
            "Reference": "010414DE", 
            "Count": 1, 
            "Unused": "8F 1E"
        }, 
        {
            "Level": 1, 
            "Unused": "8F 1E", 
            "Reference": "010414E2", 
            "Count": 1, 
            "Unused": "8F 1E"
        }, 
        {
            "Level": 1, 
            "Unused": "8F 1E", 
            "Reference": "011200B5", 
            "Count": 1, 
            "Unused": "8F 1E"
        }, 
        {
            "Level": 1, 
            "Unused": "8F 1E", 
            "Reference": "011200B7", 
            "Count": 1, 
            "Unused": "8F 1E"
        }, 
        {
            "Level": 1, 
            "Unused": "8F 1E", 
            "Reference": "011200B8", 
            "Count": 1, 
            "Unused": "8F 1E"
        }
    ]
}
