{
    "Cell": " [CELL:014C0817]", 
    "Record Header": {
        "Signature": "REFR", 
        "Data Size": 40, 
        "Record Flags": {}, 
        "FormID": "0185DE4D", 
        "Version Control Info": "00 00 00 00"
    }, 
    "NAME - Base": "0activeUsignUMtUAU01 [ACTI:010E01C5]", 
    "DATA - Position/Rotation": {
        "Position": {
            "X": 73054.507812000000000, 
            "Y": 37782.511719000000000, 
            "Z": 1564.230957000000000
        }, 
        "Rotation": {
            "X": 0.000000000000000, 
            "Y": 0.000000000000000, 
            "Z": 296.974600000000000
        }
    }
}
