{
    "Cell": " [CELL:014C13F8]", 
    "Record Header": {
        "Signature": "REFR", 
        "Data Size": 50, 
        "Record Flags": {}, 
        "FormID": "018719A2", 
        "Version Control Info": "00 00 00 00"
    }, 
    "NAME - Base": "0FloraUkelpU02 [STAT:010C0A73]", 
    "XSCL - Scale": 1.540000000000000, 
    "DATA - Position/Rotation": {
        "Position": {
            "X": -80552.195312000000000, 
            "Y": 44394.027344000000000, 
            "Z": -391.099854000000000
        }, 
        "Rotation": {
            "X": 0.000000000000000, 
            "Y": 0.000000000000000, 
            "Z": 192.878700000000000
        }
    }
}
