{
    "Cell": " [CELL:014C0694]", 
    "Record Header": {
        "Signature": "REFR", 
        "Data Size": 40, 
        "Record Flags": {}, 
        "FormID": "01819F39", 
        "Version Control Info": "00 00 00 00"
    }, 
    "NAME - Base": "0floraUwickwheatU03 [FLOR:011E0155]", 
    "DATA - Position/Rotation": {
        "Position": {
            "X": 82969.906250000000000, 
            "Y": 85544.773438000000000, 
            "Z": 1207.810669000000000
        }, 
        "Rotation": {
            "X": 0.000000000000000, 
            "Y": 0.000000000000000, 
            "Z": 13.335600000000000
        }
    }
}
