{
    "Cell": "AldTruhnVSTuvesoSBelethXSSmith [CELL:014800BA]", 
    "Record Header": {
        "Signature": "REFR", 
        "Data Size": 40, 
        "Record Flags": {}, 
        "FormID": "01820508", 
        "Version Control Info": "00 00 00 00"
    }, 
    "NAME - Base": "0chitinSgreaves [ARMO:01120004]", 
    "DATA - Position/Rotation": {
        "Position": {
            "X": 488.000000000000000, 
            "Y": 332.000000000000000, 
            "Z": -70.453903000000000
        }, 
        "Rotation": {
            "X": 0.000000000000000, 
            "Y": 0.000000000000000, 
            "Z": 0.000000000000000
        }
    }
}
