{
    "Cell": "VivecVSTelvanniSPlaza [CELL:01480487]", 
    "Record Header": {
        "Signature": "REFR", 
        "Data Size": 50, 
        "Record Flags": {}, 
        "FormID": "01872213", 
        "Version Control Info": "00 00 00 00"
    }, 
    "NAME - Base": "0floraUgrassU02 [STAT:010C00E0]", 
    "XSCL - Scale": 1.260000000000000, 
    "DATA - Position/Rotation": {
        "Position": {
            "X": 1019.347534000000000, 
            "Y": -228.830231000000000, 
            "Z": -934.648926000000000
        }, 
        "Rotation": {
            "X": 0.000000000000000, 
            "Y": 0.000000000000000, 
            "Z": 334.216900000000000
        }
    }
}
