{
    "Record Header": {
        "Signature": "LIGH", 
        "Data Size": 66, 
        "Record Flags": {}, 
        "FormID": "012C000E", 
        "Version Control Info": "00 00 00 00"
    }, 
    "EDID - Editor ID": "0blueSlight", 
    "DATA - DATA": {
        "Time": -1, 
        "Radius": "00000600", 
        "Color": {
            "Red": "1E", 
            "Green": "20", 
            "Blue": "60", 
            "Unused": "00"
        }, 
        "Flags": {
            "Dynamic": true
        }, 
        "Falloff Exponent": 1.000000000000000, 
        "FOV": 90.000000000000000, 
        "Value": 0, 
        "Weight": 0.000000000000000
    }, 
    "FNAM - Fade value": 0.330000000000000
}
