{
    "Cell": "NchardumzSLowerSLevel [CELL:014802B2]", 
    "Record Header": {
        "Signature": "REFR", 
        "Data Size": 40, 
        "Record Flags": {}, 
        "FormID": "0186531E", 
        "Version Control Info": "00 00 00 00"
    }, 
    "NAME - Base": "0miscUdwrvUgoblet00 [MISC:0116009D]", 
    "DATA - Position/Rotation": {
        "Position": {
            "X": 568.905701000000000, 
            "Y": 579.049683000000000, 
            "Z": -174.030518000000000
        }, 
        "Rotation": {
            "X": 0.000000000000000, 
            "Y": 0.000000000000000, 
            "Z": 0.000000000000000
        }
    }
}
