{
    "Cell": " [CELL:014C07D8]", 
    "Record Header": {
        "Signature": "REFR", 
        "Data Size": 40, 
        "Record Flags": {}, 
        "FormID": "0186A6B3", 
        "Version Control Info": "00 00 00 00"
    }, 
    "NAME - Base": "0blueScoastSrefS1024 [LIGH:012C01D8]", 
    "DATA - Position/Rotation": {
        "Position": {
            "X": 68293.578125000000000, 
            "Y": 159198.062500000000000, 
            "Z": -340.211639000000000
        }, 
        "Rotation": {
            "X": 0.000000000000000, 
            "Y": 0.000000000000000, 
            "Z": 160.428100000000000
        }
    }
}
