{
    "Cell": " [CELL:014C133B]", 
    "Record Header": {
        "Signature": "REFR", 
        "Data Size": 50, 
        "Record Flags": {}, 
        "FormID": "018655ED", 
        "Version Control Info": "00 00 00 00"
    }, 
    "NAME - Base": "0FloraUkelpU01 [STAT:010C0A72]", 
    "XSCL - Scale": 1.820000000000000, 
    "DATA - Position/Rotation": {
        "Position": {
            "X": -67006.875000000000000, 
            "Y": 154330.015625000000000, 
            "Z": -1137.487793000000000
        }, 
        "Rotation": {
            "X": 0.000000000000000, 
            "Y": 0.000000000000000, 
            "Z": 354.270500000000000
        }
    }
}
