{
    "Cell": " [CELL:014C117B]", 
    "Record Header": {
        "Signature": "REFR", 
        "Data Size": 50, 
        "Record Flags": {}, 
        "FormID": "01866386", 
        "Version Control Info": "00 00 00 00"
    }, 
    "NAME - Base": "0FloraUkelpU02 [STAT:010C0A73]", 
    "XSCL - Scale": 1.540000000000000, 
    "DATA - Position/Rotation": {
        "Position": {
            "X": -42717.992188000000000, 
            "Y": 162771.281250000000000, 
            "Z": -1710.154297000000000
        }, 
        "Rotation": {
            "X": 0.000000000000000, 
            "Y": 348.540900000000000, 
            "Z": 126.050700000000000
        }
    }
}
