{
    "Cell": "AkulakhanAsSChamber [CELL:01480073]", 
    "Record Header": {
        "Signature": "REFR", 
        "Data Size": 68, 
        "Record Flags": {
            "Quest item / Persistent reference / Show in Menu": true
        }, 
        "FormID": "01001B45", 
        "Version Control Info": "00 00 00 00"
    }, 
    "EDID - Editor ID": "mwDagothUrDefendHeart", 
    "NAME - Base": "XMarkerHeading [STAT:00000034]", 
    "DATA - Position/Rotation": {
        "Position": {
            "X": -191.932861000000000, 
            "Y": 3738.249023000000000, 
            "Z": -226.381378000000000
        }, 
        "Rotation": {
            "X": 0.000000000000000, 
            "Y": 0.000000000000000, 
            "Z": 97.402900000000000
        }
    }
}
