{
    "Cell": "SolstheimVSGyldenhulSBarrowSEntrance00 [CELL:014C1604]", 
    "Record Header": {
        "Signature": "REFR", 
        "Data Size": 50, 
        "Record Flags": {}, 
        "FormID": "01F034F3", 
        "Version Control Info": "00 00 00 00"
    }, 
    "NAME - Base": "0TerrainUBMUicechunkU08 [STAT:010C0C8E]", 
    "XSCL - Scale": 0.580000000000000, 
    "DATA - Position/Rotation": {
        "Position": {
            "X": -137260.328125000000000, 
            "Y": 199714.296875000000000, 
            "Z": 0.385385000000000
        }, 
        "Rotation": {
            "X": 0.000000000000000, 
            "Y": 0.000000000000000, 
            "Z": 11.459200000000000
        }
    }
}
