{
    "Cell": "AncientSShipwreckVSUpperSLevel [CELL:014800C7]", 
    "Record Header": {
        "Signature": "REFR", 
        "Data Size": 50, 
        "Record Flags": {}, 
        "FormID": "0184C82D", 
        "Version Control Info": "00 00 00 00"
    }, 
    "NAME - Base": "0barrelU01UdeUpos1 [CONT:011C00AD]", 
    "XSCL - Scale": 0.950000000000000, 
    "DATA - Position/Rotation": {
        "Position": {
            "X": 4457.722168000000000, 
            "Y": 3891.276123000000000, 
            "Z": 74.445427000000000
        }, 
        "Rotation": {
            "X": 18.000000000000000, 
            "Y": 0.000000000000000, 
            "Z": 90.000000000000000
        }
    }
}
