{
    "Cell": " [CELL:014C0852]", 
    "Record Header": {
        "Signature": "REFR", 
        "Data Size": 40, 
        "Record Flags": {}, 
        "FormID": "0181CD9A", 
        "Version Control Info": "00 00 00 00"
    }, 
    "NAME - Base": "0floraUmarshmerrowU02 [FLOR:011E014F]", 
    "DATA - Position/Rotation": {
        "Position": {
            "X": 69393.773438000000000, 
            "Y": -82022.078125000000000, 
            "Z": 43.554230000000000
        }, 
        "Rotation": {
            "X": 0.000000000000000, 
            "Y": 0.000000000000000, 
            "Z": 74.484500000000000
        }
    }
}
